{
  "phrases": [
    {
      "english": "Thank you, truly.",
      "serbian": "Хвала, заиста.",
      "transliteration": "Hvala, zaista.",
      "category": "Gratitude",
      "generated_at": "2026-06-17T11:51:12.382184"
    },
    {
      "english": "I'm so grateful, sincerely.",
      "serbian": "Искрено сам захвалан/захвална.",
      "transliteration": "Iskreno sam zahvalan/zahvalna.",
      "category": "Gratitude",
      "generated_at": "2026-06-17T11:51:12.382192"
    },
    {
      "english": "This means a lot, thank you.",
      "serbian": "Ово пуно значи, хвала.",
      "transliteration": "Ovo puno znači, hvala.",
      "category": "Gratitude",
      "generated_at": "2026-06-17T11:51:12.382193"
    },
    {
      "english": "Your kindness, appreciated.",
      "serbian": "Ваша љубазност, цењена.",
      "transliteration": "Vaša ljubaznost, cenjena.",
      "category": "Gratitude",
      "generated_at": "2026-06-17T11:51:12.382195"
    },
    {
      "english": "Deepest thanks, to you.",
      "serbian": "Најдубље хвала, вама.",
      "transliteration": "Najdublje hvala, vama.",
      "category": "Gratitude",
      "generated_at": "2026-06-17T11:51:12.382196"
    },
    {
      "english": "Be strong, believe.",
      "serbian": "Буди јак, веруј.",
      "transliteration": "Budi jak, veruj.",
      "category": "Strength",
      "generated_at": "2026-06-17T12:37:37.475918"
    },
    {
      "english": "Inner strength, shines bright.",
      "serbian": "Унутрашња снага, сија јако.",
      "transliteration": "Unutrašnja snaga, sija jako.",
      "category": "Strength",
      "generated_at": "2026-06-17T12:37:37.475924"
    },
    {
      "english": "Rise up, never give in.",
      "serbian": "Устани, никад не одустај.",
      "transliteration": "Ustani, nikad ne odustaj.",
      "category": "Strength",
      "generated_at": "2026-06-17T12:37:37.475926"
    },
    {
      "english": "Your courage, is your power.",
      "serbian": "Твоја храброст, је твоја моћ.",
      "transliteration": "Tvoja hrabrost, je tvoja moć.",
      "category": "Strength",
      "generated_at": "2026-06-17T12:37:37.475927"
    },
    {
      "english": "Find your fire, and burn.",
      "serbian": "Пронађи своју ватру, и гори.",
      "transliteration": "Pronađi svoju vatru, i gori.",
      "category": "Strength",
      "generated_at": "2026-06-17T12:37:37.475928"
    },
    {
      "english": "Where can I find, the nearest store?",
      "serbian": "Где је, најближа продавница?",
      "transliteration": "Gde je, najbilža prodavnica?",
      "category": "Shopping",
      "generated_at": "2026-06-17T15:23:14.466536"
    },
    {
      "english": "How much is this, please?",
      "serbian": "Колико је, ово, молим?",
      "transliteration": "Koliko je, ovo, molim?",
      "category": "Shopping",
      "generated_at": "2026-06-17T15:23:14.466544"
    },
    {
      "english": "I am looking for, a souvenir.",
      "serbian": "Тражим, сувенир.",
      "transliteration": "Tražim, suvenir.",
      "category": "Shopping",
      "generated_at": "2026-06-17T15:23:14.466546"
    },
    {
      "english": "Do you have, this in blue?",
      "serbian": "Имате ли, ово, плаво?",
      "transliteration": "Imate li, ovo, plavo?",
      "category": "Shopping",
      "generated_at": "2026-06-17T15:23:14.466551"
    },
    {
      "english": "Can I try, this on?",
      "serbian": "Могу ли, да пробам, ово?",
      "transliteration": "Mogu li, da probam, ovo?",
      "category": "Shopping",
      "generated_at": "2026-06-17T15:23:14.466552"
    }
  ],
  "last_updated": "2026-06-17T15:23:14.466556"
}