{
  "phrases": [
    {
      "english": "Thank you, truly.",
      "serbian": "Хвала, заиста.",
      "transliteration": "Hvala, zaista.",
      "category": "Gratitude",
      "generated_at": "2026-06-17T11:51:12.382184"
    },
    {
      "english": "I'm so grateful, sincerely.",
      "serbian": "Искрено сам захвалан/захвална.",
      "transliteration": "Iskreno sam zahvalan/zahvalna.",
      "category": "Gratitude",
      "generated_at": "2026-06-17T11:51:12.382192"
    },
    {
      "english": "This means a lot, thank you.",
      "serbian": "Ово пуно значи, хвала.",
      "transliteration": "Ovo puno znači, hvala.",
      "category": "Gratitude",
      "generated_at": "2026-06-17T11:51:12.382193"
    },
    {
      "english": "Your kindness, appreciated.",
      "serbian": "Ваша љубазност, цењена.",
      "transliteration": "Vaša ljubaznost, cenjena.",
      "category": "Gratitude",
      "generated_at": "2026-06-17T11:51:12.382195"
    },
    {
      "english": "Deepest thanks, to you.",
      "serbian": "Најдубље хвала, вама.",
      "transliteration": "Najdublje hvala, vama.",
      "category": "Gratitude",
      "generated_at": "2026-06-17T11:51:12.382196"
    },
    {
      "english": "Be strong, believe.",
      "serbian": "Буди јак, веруј.",
      "transliteration": "Budi jak, veruj.",
      "category": "Strength",
      "generated_at": "2026-06-17T12:37:37.475918"
    },
    {
      "english": "Inner strength, shines bright.",
      "serbian": "Унутрашња снага, сија јако.",
      "transliteration": "Unutrašnja snaga, sija jako.",
      "category": "Strength",
      "generated_at": "2026-06-17T12:37:37.475924"
    },
    {
      "english": "Rise up, never give in.",
      "serbian": "Устани, никад не одустај.",
      "transliteration": "Ustani, nikad ne odustaj.",
      "category": "Strength",
      "generated_at": "2026-06-17T12:37:37.475926"
    },
    {
      "english": "Your courage, is your power.",
      "serbian": "Твоја храброст, је твоја моћ.",
      "transliteration": "Tvoja hrabrost, je tvoja moć.",
      "category": "Strength",
      "generated_at": "2026-06-17T12:37:37.475927"
    },
    {
      "english": "Find your fire, and burn.",
      "serbian": "Пронађи своју ватру, и гори.",
      "transliteration": "Pronađi svoju vatru, i gori.",
      "category": "Strength",
      "generated_at": "2026-06-17T12:37:37.475928"
    },
    {
      "english": "Where can I find, the nearest store?",
      "serbian": "Где је, најближа продавница?",
      "transliteration": "Gde je, najbilža prodavnica?",
      "category": "Shopping",
      "generated_at": "2026-06-17T15:23:14.466536"
    },
    {
      "english": "How much is this, please?",
      "serbian": "Колико је, ово, молим?",
      "transliteration": "Koliko je, ovo, molim?",
      "category": "Shopping",
      "generated_at": "2026-06-17T15:23:14.466544"
    },
    {
      "english": "I am looking for, a souvenir.",
      "serbian": "Тражим, сувенир.",
      "transliteration": "Tražim, suvenir.",
      "category": "Shopping",
      "generated_at": "2026-06-17T15:23:14.466546"
    },
    {
      "english": "Do you have, this in blue?",
      "serbian": "Имате ли, ово, плаво?",
      "transliteration": "Imate li, ovo, plavo?",
      "category": "Shopping",
      "generated_at": "2026-06-17T15:23:14.466551"
    },
    {
      "english": "Can I try, this on?",
      "serbian": "Могу ли, да пробам, ово?",
      "transliteration": "Mogu li, da probam, ovo?",
      "category": "Shopping",
      "generated_at": "2026-06-17T15:23:14.466552"
    },
    {
      "english": "I'm truly sorry, please forgive me.",
      "serbian": "Zaista mi je žao, molim te oprosti mi.",
      "transliteration": "Zai-sta mi je zao, mo-lim te opros-ti mi.",
      "category": "Forgiveness",
      "generated_at": "2026-06-17T17:13:38.768882"
    },
    {
      "english": "Let's move past this, okay?",
      "serbian": "Hajde da ovo ostavimo iza nas, važi?",
      "transliteration": "Haj-de da o-vo os-tav-i-mo i-za nas, va-zi?",
      "category": "Forgiveness",
      "generated_at": "2026-06-17T17:13:38.768889"
    },
    {
      "english": "I hope you can forgive me.",
      "serbian": "Nadam se da mi možeš oprostiti.",
      "transliteration": "Na-dam se da mi mo-zhes opros-ti-ti.",
      "category": "Forgiveness",
      "generated_at": "2026-06-17T17:13:38.768890"
    },
    {
      "english": "It was my mistake, I apologize.",
      "serbian": "Moja je greška, izvinjavam se.",
      "transliteration": "Mo-ja je gresh-ka, iz-vi-nja-vam se.",
      "category": "Forgiveness",
      "generated_at": "2026-06-17T17:13:38.768892"
    },
    {
      "english": "Can we start fresh now?",
      "serbian": "Možemo li sada početi iznova?",
      "transliteration": "Mo-zhe-mo li sa-da po-che-ti iz-no-va?",
      "category": "Forgiveness",
      "generated_at": "2026-06-17T17:13:38.768893"
    },
    {
      "english": "Help! I need a doctor, please.",
      "serbian": "У помоћ! Треба ми лекар, молим.",
      "transliteration": "U pomoc! Treba mi lekar, molim.",
      "category": "Emergency",
      "generated_at": "2026-06-17T19:17:44.274824"
    },
    {
      "english": "Is there a hospital, nearby?",
      "serbian": "Има ли болница, у близини?",
      "transliteration": "Ima li bolnica, u blizini?",
      "category": "Emergency",
      "generated_at": "2026-06-17T19:17:44.274832"
    },
    {
      "english": "I am lost, can you help?",
      "serbian": "Изгубио/изгубила сам се, можете ли помоћи?",
      "transliteration": "Izgubio/izgubila sam se, mozete li pomoci?",
      "category": "Emergency",
      "generated_at": "2026-06-17T19:17:44.274834"
    },
    {
      "english": "Call the police, immediately!",
      "serbian": "Зовите полицију, одмах!",
      "transliteration": "Zovite policiju, odmah!",
      "category": "Emergency",
      "generated_at": "2026-06-17T19:17:44.274836"
    },
    {
      "english": "My passport is stolen, help!",
      "serbian": "Украли су ми пасош, помозите!",
      "transliteration": "Ukrali su mi pasos, pomozite!",
      "category": "Emergency",
      "generated_at": "2026-06-17T19:17:44.274837"
    },
    {
      "english": "Be kind, always.",
      "serbian": "Budi ljubazan, uvek.",
      "transliteration": "Boo-dee lyoo-bah-zahn, oo-vehk.",
      "category": "Kindness",
      "generated_at": "2026-06-17T22:03:54.309305"
    },
    {
      "english": "Your smile, it helps.",
      "serbian": "Tvoj osmeh, pomaže.",
      "transliteration": "Tvoy oh-smeh, poh-mah-zheh.",
      "category": "Kindness",
      "generated_at": "2026-06-17T22:03:54.309313"
    },
    {
      "english": "Little good deeds, matter.",
      "serbian": "Mala dobra dela, znače.",
      "transliteration": "Mah-lah doh-brah deh-lah, znah-cheh.",
      "category": "Kindness",
      "generated_at": "2026-06-17T22:03:54.309314"
    },
    {
      "english": "Share your joy, freely.",
      "serbian": "Deli svoju radost, slobodno.",
      "transliteration": "Deh-lee svoh-yoo rah-dohst, sloh-boh-dno.",
      "category": "Kindness",
      "generated_at": "2026-06-17T22:03:54.309316"
    },
    {
      "english": "Listen with heart, truly.",
      "serbian": "Slušaj srcem, iskreno.",
      "transliteration": "Sloo-shy ser-tsem, ees-kreh-no.",
      "category": "Kindness",
      "generated_at": "2026-06-17T22:03:54.309317"
    },
    {
      "english": "My mother, she is kind.",
      "serbian": "Moja majka, ona je dobra.",
      "transliteration": "Moya majka, ona ye dobra.",
      "category": "Family Terms",
      "generated_at": "2026-06-18T03:40:05.554911"
    },
    {
      "english": "Your father, he works hard.",
      "serbian": "Tvoj otac, on mnogo radi.",
      "transliteration": "Tvoy otac, on mnogo radi.",
      "category": "Family Terms",
      "generated_at": "2026-06-18T03:40:05.554917"
    },
    {
      "english": "Our sister, she is young.",
      "serbian": "Naša sestra, ona je mlada.",
      "transliteration": "Nasha sestra, ona ye mlada.",
      "category": "Family Terms",
      "generated_at": "2026-06-18T03:40:05.554919"
    },
    {
      "english": "Their brother, he is tall.",
      "serbian": "Njihov brat, on je visok.",
      "transliteration": "Nihov brat, on ye visok.",
      "category": "Family Terms",
      "generated_at": "2026-06-18T03:40:05.554920"
    },
    {
      "english": "My grandmother, she bakes well.",
      "serbian": "Moja baka, ona dobro peče.",
      "transliteration": "Moya baka, ona dobro peche.",
      "category": "Family Terms",
      "generated_at": "2026-06-18T03:40:05.554921"
    },
    {
      "english": "Learn daily, grow stronger.",
      "serbian": "Uči svakodnevno, rasti jače.",
      "transliteration": "Uchi svakodnevno, rasti jache.",
      "category": "Self Improvement",
      "generated_at": "2026-06-18T16:29:14.889635"
    },
    {
      "english": "Listen more, speak less.",
      "serbian": "Slušaj više, govori manje.",
      "transliteration": "Slushaj vishe, govori manje.",
      "category": "Self Improvement",
      "generated_at": "2026-06-18T16:29:14.889643"
    },
    {
      "english": "Embrace change, find joy.",
      "serbian": "Prihvati promenu, nađi radost.",
      "transliteration": "Prihvati promenu, nadji radost.",
      "category": "Self Improvement",
      "generated_at": "2026-06-18T16:29:14.889645"
    },
    {
      "english": "Believe in yourself, truly.",
      "serbian": "Veruj u sebe, iskreno.",
      "transliteration": "Veruj u sebe, iskreno.",
      "category": "Self Improvement",
      "generated_at": "2026-06-18T16:29:14.889647"
    },
    {
      "english": "Stay curious, explore more.",
      "serbian": "Ostani radoznao, istražuj više.",
      "transliteration": "Ostani radoznao, istrazhuj vishe.",
      "category": "Self Improvement",
      "generated_at": "2026-06-18T16:29:14.889648"
    },
    {
      "english": "Imagine, create, inspire.",
      "serbian": "Замисли, створи, инспириши.",
      "transliteration": "Zamislí, stvorí, inspiríši.",
      "category": "Creativity",
      "generated_at": "2026-06-18T17:30:29.824827"
    },
    {
      "english": "Let your mind wander.",
      "serbian": "Пусти ум да лута.",
      "transliteration": "Pusti um da luta.",
      "category": "Creativity",
      "generated_at": "2026-06-18T17:30:29.824835"
    },
    {
      "english": "New ideas, fresh start.",
      "serbian": "Нове идеје, свеж почетак.",
      "transliteration": "Nove ideje, svež početak.",
      "category": "Creativity",
      "generated_at": "2026-06-18T17:30:29.824837"
    },
    {
      "english": "Think outside the box.",
      "serbian": "Мисли изван оквира.",
      "transliteration": "Misli izvan okvira.",
      "category": "Creativity",
      "generated_at": "2026-06-18T17:30:29.824838"
    },
    {
      "english": "Your vision, your art.",
      "serbian": "Твоја визија, твоја уметност.",
      "transliteration": "Tvoja vizija, tvoja umetnost.",
      "category": "Creativity",
      "generated_at": "2026-06-18T17:30:29.824839"
    },
    {
      "english": "You're doing great, keep going.",
      "serbian": "Odlično ti ide, samo napred.",
      "transliteration": "Odlichno ti ide, samo napred.",
      "category": "Success",
      "generated_at": "2026-06-18T19:17:10.293720"
    },
    {
      "english": "Little by little, you'll get there.",
      "serbian": "Malo po malo, stići ćeš.",
      "transliteration": "Malo po malo, stichi chesh.",
      "category": "Success",
      "generated_at": "2026-06-18T19:17:10.293730"
    },
    {
      "english": "Your progress is visible, bravo!",
      "serbian": "Tvoj napredak je vidljiv, bravo!",
      "transliteration": "Tvoj napredak je vidljiv, bravo!",
      "category": "Success",
      "generated_at": "2026-06-18T19:17:10.293732"
    },
    {
      "english": "Practice makes perfect, keep it up.",
      "serbian": "Vežba čini majstora, nastavi tako.",
      "transliteration": "Vezhba chini majstora, nastavi tako.",
      "category": "Success",
      "generated_at": "2026-06-18T19:17:10.293733"
    },
    {
      "english": "Every word counts, listen well.",
      "serbian": "Svaka reč je bitna, slušaj pažljivo.",
      "transliteration": "Svaka rech je bitna, slushaj pazhljivo.",
      "category": "Success",
      "generated_at": "2026-06-18T19:17:10.293735"
    },
    {
      "english": "Learn today, speak tomorrow.",
      "serbian": "Uči danas, govori sutra.",
      "transliteration": "Uči danas, govori sutra.",
      "category": "Inspiration",
      "generated_at": "2026-06-18T22:28:08.675595"
    },
    {
      "english": "Every word, a new step.",
      "serbian": "Svaka reč, novi korak.",
      "transliteration": "Svaka reč, novi korak.",
      "category": "Inspiration",
      "generated_at": "2026-06-18T22:28:08.675605"
    },
    {
      "english": "Be brave, be curious.",
      "serbian": "Budi hrabar, budi znatiželjan.",
      "transliteration": "Budi hrabar, budi znatiželjan.",
      "category": "Inspiration",
      "generated_at": "2026-06-18T22:28:08.675607"
    },
    {
      "english": "Your voice matters, speak it.",
      "serbian": "Tvoj glas je važan, izgovori ga.",
      "transliteration": "Tvoj glas je važan, izgovori ga.",
      "category": "Inspiration",
      "generated_at": "2026-06-18T22:28:08.675608"
    },
    {
      "english": "Don't fear mistakes, learn from them.",
      "serbian": "Ne boj se grešaka, uči iz njih.",
      "transliteration": "Ne boj se grešaka, uči iz njih.",
      "category": "Inspiration",
      "generated_at": "2026-06-18T22:28:08.675609"
    },
    {
      "english": "Slowly, but surely.",
      "serbian": "Полако, али сигурно.",
      "transliteration": "Polako, ali sigurno.",
      "category": "Patience",
      "generated_at": "2026-06-19T04:03:16.387246"
    },
    {
      "english": "One step, at a time.",
      "serbian": "Један корак, по један.",
      "transliteration": "Jedan korak, po jedan.",
      "category": "Patience",
      "generated_at": "2026-06-19T04:03:16.387254"
    },
    {
      "english": "Good things, take time.",
      "serbian": "Добре ствари, траже време.",
      "transliteration": "Dobre stvari, traže vreme.",
      "category": "Patience",
      "generated_at": "2026-06-19T04:03:16.387256"
    },
    {
      "english": "Keep trying, don't give up.",
      "serbian": "Настави да покушаваш, не одустај.",
      "transliteration": "Nastavi da pokušavaš, ne odustaj.",
      "category": "Patience",
      "generated_at": "2026-06-19T04:03:16.387257"
    },
    {
      "english": "It will happen, eventually.",
      "serbian": "Десиће се, на крају.",
      "transliteration": "Desiće se, na kraju.",
      "category": "Patience",
      "generated_at": "2026-06-19T04:03:16.387258"
    },
    {
      "english": "No problem, at all.",
      "serbian": "Није проблем, уопште.",
      "transliteration": "Nije problem, uopšte.",
      "category": "Common Expressions",
      "generated_at": "2026-06-19T15:11:24.115825"
    },
    {
      "english": "Take your time, please.",
      "serbian": "Полако, молим Вас.",
      "transliteration": "Polako, molim Vas.",
      "category": "Common Expressions",
      "generated_at": "2026-06-19T15:11:24.115834"
    },
    {
      "english": "How can I help?",
      "serbian": "Како могу помоћи?",
      "transliteration": "Kako mogu pomoći?",
      "category": "Common Expressions",
      "generated_at": "2026-06-19T15:11:24.115836"
    },
    {
      "english": "See you soon, okay?",
      "serbian": "Видимо се ускоро, важи?",
      "transliteration": "Vidimo se uskoro, važi?",
      "category": "Common Expressions",
      "generated_at": "2026-06-19T15:11:24.115837"
    },
    {
      "english": "Just a moment, please.",
      "serbian": "Само тренутак, молим.",
      "transliteration": "Samo trenutak, molim.",
      "category": "Common Expressions",
      "generated_at": "2026-06-19T15:11:24.115838"
    },
    {
      "english": "Hello, how are you?",
      "serbian": "Здраво, како сте?",
      "transliteration": "Zdravo, kako ste?",
      "category": "Basic Phrases",
      "generated_at": "2026-06-19T16:36:02.544925"
    },
    {
      "english": "Thank you, very much.",
      "serbian": "Хвала, пуно.",
      "transliteration": "Hvala, puno.",
      "category": "Basic Phrases",
      "generated_at": "2026-06-19T16:36:02.544936"
    },
    {
      "english": "Excuse me, please.",
      "serbian": "Извините, молим.",
      "transliteration": "Izvinite, molim.",
      "category": "Basic Phrases",
      "generated_at": "2026-06-19T16:36:02.544938"
    },
    {
      "english": "I don't understand.",
      "serbian": "Не разумем.",
      "transliteration": "Ne razumem.",
      "category": "Basic Phrases",
      "generated_at": "2026-06-19T16:36:02.544940"
    },
    {
      "english": "Yes, of course.",
      "serbian": "Да, наравно.",
      "transliteration": "Da, naravno.",
      "category": "Basic Phrases",
      "generated_at": "2026-06-19T16:36:02.544941"
    },
    {
      "english": "Joyful heart, happy life.",
      "serbian": "Радосно срце, срећан живот.",
      "transliteration": "Radosno srce, srećan život.",
      "category": "Happiness",
      "generated_at": "2026-06-19T18:28:08.186255"
    },
    {
      "english": "Smile often, laugh loudly.",
      "serbian": "Смеј се често, смеј се гласно.",
      "transliteration": "Smej se često, smej se glasno.",
      "category": "Happiness",
      "generated_at": "2026-06-19T18:28:08.186263"
    },
    {
      "english": "Find peace, feel good.",
      "serbian": "Нађи мир, осети добро.",
      "transliteration": "Nađi mir, oseti dobro.",
      "category": "Happiness",
      "generated_at": "2026-06-19T18:28:08.186264"
    },
    {
      "english": "Good day, good mood.",
      "serbian": "Добар дан, добро расположење.",
      "transliteration": "Dobar dan, dobro raspoloženje.",
      "category": "Happiness",
      "generated_at": "2026-06-19T18:28:08.186269"
    },
    {
      "english": "Simple pleasures, great joy.",
      "serbian": "Једноставна задовољства, велика радост.",
      "transliteration": "Jednostavna zadovoljstva, velika radost.",
      "category": "Happiness",
      "generated_at": "2026-06-19T18:28:08.186270"
    },
    {
      "english": "Be brave, little one.",
      "serbian": "Буди храбар, мали.",
      "transliteration": "Budi hrabar, mali.",
      "category": "Courage",
      "generated_at": "2026-06-19T21:12:57.382222"
    },
    {
      "english": "Face your fears, openly.",
      "serbian": "Суочи се са страховима, отворено.",
      "transliteration": "Suoči se sa strahovima, otvoreno.",
      "category": "Courage",
      "generated_at": "2026-06-19T21:12:57.382229"
    },
    {
      "english": "You are stronger, than you think.",
      "serbian": "Јачи си, него што мислиш.",
      "transliteration": "Jači si, nego što misliš.",
      "category": "Courage",
      "generated_at": "2026-06-19T21:12:57.382231"
    },
    {
      "english": "Take a deep breath, then go.",
      "serbian": "Удахни дубоко, па крени.",
      "transliteration": "Udahniduboko, pa kreni.",
      "category": "Courage",
      "generated_at": "2026-06-19T21:12:57.382233"
    },
    {
      "english": "Action conquers, all doubt.",
      "serbian": "Акција побеђује, све сумње.",
      "transliteration": "Akcija pobeđuje, sve sumnje.",
      "category": "Courage",
      "generated_at": "2026-06-19T21:12:57.382234"
    },
    {
      "english": "You're my best friend, always.",
      "serbian": "Ti si moj najbolji prijatelj, uvek.",
      "transliteration": "Ti si moj najbolji prijatelj, uvek.",
      "category": "Friendship",
      "generated_at": "2026-06-20T03:26:21.948388"
    },
    {
      "english": "We've been friends, for years.",
      "serbian": "Prijatelji smo, mnogo godina.",
      "transliteration": "Prijatelji smo, mnogo godina.",
      "category": "Friendship",
      "generated_at": "2026-06-20T03:26:21.948398"
    },
    {
      "english": "Thanks for everything, truly.",
      "serbian": "Hvala ti za sve, iskreno.",
      "transliteration": "Hvala ti za sve, iskreno.",
      "category": "Friendship",
      "generated_at": "2026-06-20T03:26:21.948400"
    },
    {
      "english": "Let's hang out, soon.",
      "serbian": "Hajde da se vidimo, uskoro.",
      "transliteration": "Hajde da se vidimo, uskoro.",
      "category": "Friendship",
      "generated_at": "2026-06-20T03:26:21.948401"
    },
    {
      "english": "I appreciate you, a lot.",
      "serbian": "Cenim te, puno.",
      "transliteration": "Cenim te, puno.",
      "category": "Friendship",
      "generated_at": "2026-06-20T03:26:21.948402"
    },
    {
      "english": "Where is the bathroom?",
      "serbian": "Где је тоалет?",
      "transliteration": "Gde je toalet?",
      "category": "Travel",
      "generated_at": "2026-06-20T13:58:49.655413"
    },
    {
      "english": "How much does this cost?",
      "serbian": "Колико ово кошта?",
      "transliteration": "Koliko ovo košta?",
      "category": "Travel",
      "generated_at": "2026-06-20T13:58:49.655424"
    },
    {
      "english": "I need help, please.",
      "serbian": "Треба ми помоћ, молим.",
      "transliteration": "Treba mi pomoć, molim.",
      "category": "Travel",
      "generated_at": "2026-06-20T13:58:49.655426"
    },
    {
      "english": "One ticket to Belgrade.",
      "serbian": "Једну карту за Београд.",
      "transliteration": "Jednu kartu za Beograd.",
      "category": "Travel",
      "generated_at": "2026-06-20T13:58:49.655427"
    },
    {
      "english": "Do you speak English?",
      "serbian": "Говорите ли енглески?",
      "transliteration": "Govorite li engleski?",
      "category": "Travel",
      "generated_at": "2026-06-20T13:58:49.655428"
    },
    {
      "english": "One, two, three, go!",
      "serbian": "Jedan, dva, tri, kreni!",
      "transliteration": "Yedan, dva, tri, kreni!",
      "category": "Numbers",
      "generated_at": "2026-06-20T15:49:14.476484"
    },
    {
      "english": "Five, then ten, slowly.",
      "serbian": "Pet, pa deset, polako.",
      "transliteration": "Pet, pa des-et, polako.",
      "category": "Numbers",
      "generated_at": "2026-06-20T15:49:14.476492"
    },
    {
      "english": "How many, please?",
      "serbian": "Koliko, molim?",
      "transliteration": "Koliko, molim?",
      "category": "Numbers",
      "generated_at": "2026-06-20T15:49:14.476493"
    },
    {
      "english": "This costs twenty.",
      "serbian": "Ovo košta dvadeset.",
      "transliteration": "Ovo košta dvades-et.",
      "category": "Numbers",
      "generated_at": "2026-06-20T15:49:14.476495"
    },
    {
      "english": "Half, maybe less.",
      "serbian": "Pola, možda manje.",
      "transliteration": "Pola, možda manje.",
      "category": "Numbers",
      "generated_at": "2026-06-20T15:49:14.476500"
    },
    {
      "english": "I ask for your understanding.",
      "serbian": "Molim za tvoje razumevanje.",
      "transliteration": "Mo-lim za tvo-je raz-u-me-va-nje.",
      "category": "Forgiveness",
      "generated_at": "2026-06-20T18:05:27.283037"
    },
    {
      "english": "My apologies for the trouble.",
      "serbian": "Moje izvinjenje zbog problema.",
      "transliteration": "Mo-je iz-vi-nje-nje zbog pro-ble-ma.",
      "category": "Forgiveness",
      "generated_at": "2026-06-20T18:05:27.283044"
    },
    {
      "english": "I wish to mend this.",
      "serbian": "Želim ovo da popravim.",
      "transliteration": "Zhe-lim o-vo da po-pra-vim.",
      "category": "Forgiveness",
      "generated_at": "2026-06-20T18:05:27.283046"
    },
    {
      "english": "Please accept my apology.",
      "serbian": "Molim te prihvati moje izvinjenje.",
      "transliteration": "Mo-lim te pri-hva-ti mo-je iz-vi-nje-nje.",
      "category": "Forgiveness",
      "generated_at": "2026-06-20T18:05:27.283047"
    },
    {
      "english": "Let's not hold grudges.",
      "serbian": "Nemojmo držati zamerke.",
      "transliteration": "Ne-moy-mo dr-zha-ti za-mer-ke.",
      "category": "Forgiveness",
      "generated_at": "2026-06-20T18:05:27.283052"
    },
    {
      "english": "Hello there, friend.",
      "serbian": "Здраво, пријатељу.",
      "transliteration": "Zdravo, prijatelju.",
      "category": "Greetings",
      "generated_at": "2026-06-20T21:21:48.836061"
    },
    {
      "english": "Good morning, everyone.",
      "serbian": "Добро јутро, свима.",
      "transliteration": "Dobro jutro, svima.",
      "category": "Greetings",
      "generated_at": "2026-06-20T21:21:48.836070"
    },
    {
      "english": "How are you, today?",
      "serbian": "Како сте, данас?",
      "transliteration": "Kako ste, danas?",
      "category": "Greetings",
      "generated_at": "2026-06-20T21:21:48.836072"
    },
    {
      "english": "Welcome, to Serbia.",
      "serbian": "Добродошли, у Србију.",
      "transliteration": "Dobrodošli, u Srbiju.",
      "category": "Greetings",
      "generated_at": "2026-06-20T21:21:48.836073"
    },
    {
      "english": "Nice to meet you.",
      "serbian": "Драго ми је.",
      "transliteration": "Drago mi je.",
      "category": "Greetings",
      "generated_at": "2026-06-20T21:21:48.836074"
    },
    {
      "english": "Live today, love always.",
      "serbian": "Живи данас, воли увек.",
      "transliteration": "Živi danas, voli uvek.",
      "category": "Positive Life",
      "generated_at": "2026-06-21T03:56:29.040757"
    },
    {
      "english": "Find joy, in small things.",
      "serbian": "Нађи радост, у ситницама.",
      "transliteration": "Nađi radost, u sitnicama.",
      "category": "Positive Life",
      "generated_at": "2026-06-21T03:56:29.040768"
    },
    {
      "english": "Be kind, to everyone.",
      "serbian": "Буди љубазан, према свима.",
      "transliteration": "Budi ljubazan, prema svima.",
      "category": "Positive Life",
      "generated_at": "2026-06-21T03:56:29.040770"
    },
    {
      "english": "Grow strong, every day.",
      "serbian": "Расти снажно, сваки дан.",
      "transliteration": "Rasti snažno, svaki dan.",
      "category": "Positive Life",
      "generated_at": "2026-06-21T03:56:29.040771"
    },
    {
      "english": "Trust your heart, it knows.",
      "serbian": "Веруј срцу, оно зна.",
      "transliteration": "Veruj srcu, ono zna.",
      "category": "Positive Life",
      "generated_at": "2026-06-21T03:56:29.040772"
    },
    {
      "english": "Your grandfather, he tells stories.",
      "serbian": "Tvoj deda, on priča priče.",
      "transliteration": "Tvoy deda, on pricha price.",
      "category": "Family Terms",
      "generated_at": "2026-06-21T14:06:31.957437"
    },
    {
      "english": "Our aunt, she likes to travel.",
      "serbian": "Naša tetka, ona voli putovanja.",
      "transliteration": "Nasha tetka, ona voli putovanja.",
      "category": "Family Terms",
      "generated_at": "2026-06-21T14:06:31.957447"
    },
    {
      "english": "Their uncle, he is funny.",
      "serbian": "Njihov stric, on je smešan.",
      "transliteration": "Nihov stric, on ye smeshan.",
      "category": "Family Terms",
      "generated_at": "2026-06-21T14:06:31.957451"
    },
    {
      "english": "My cousin, she is smart.",
      "serbian": "Moj brat od tetke, ona je pametna.",
      "transliteration": "Moy brat od tetke, ona ye pametna.",
      "category": "Family Terms",
      "generated_at": "2026-06-21T14:06:31.957453"
    },
    {
      "english": "Your husband, he is patient.",
      "serbian": "Tvoj muž, on je strpljiv.",
      "transliteration": "Tvoy muzh, on ye strpljiv.",
      "category": "Family Terms",
      "generated_at": "2026-06-21T14:06:31.957454"
    },
    {
      "english": "I have a serious injury.",
      "serbian": "Имам озбиљну повреду.",
      "transliteration": "Imam ozbiljnu povredu.",
      "category": "Emergency",
      "generated_at": "2026-06-21T16:01:42.110811"
    },
    {
      "english": "Where is the nearest pharmacy?",
      "serbian": "Где је најближа апотека?",
      "transliteration": "Gde je najbliza apoteka?",
      "category": "Emergency",
      "generated_at": "2026-06-21T16:01:42.110820"
    },
    {
      "english": "I need an ambulance, now!",
      "serbian": "Хитно ми треба амбуланта!",
      "transliteration": "Hitno mi treba ambulanta!",
      "category": "Emergency",
      "generated_at": "2026-06-21T16:01:42.110822"
    },
    {
      "english": "My child is missing, please!",
      "serbian": "Моје дете је нестало, молим!",
      "transliteration": "Moje dete je nestalo, molim!",
      "category": "Emergency",
      "generated_at": "2026-06-21T16:01:42.110823"
    },
    {
      "english": "Fire! We need to escape.",
      "serbian": "Ватра! Морамо да бежимо.",
      "transliteration": "Vatra! Moramo da bezimo.",
      "category": "Emergency",
      "generated_at": "2026-06-21T16:01:42.110824"
    },
    {
      "english": "Stand tall, face the world.",
      "serbian": "Стани усправно, суочи се са светом.",
      "transliteration": "Stani uspravno, suoči se sa svetom.",
      "category": "Strength",
      "generated_at": "2026-06-21T18:14:52.603483"
    },
    {
      "english": "Every step, builds strength.",
      "serbian": "Сваки корак, гради снагу.",
      "transliteration": "Svaki korak, gradi snagu.",
      "category": "Strength",
      "generated_at": "2026-06-21T18:14:52.603492"
    },
    {
      "english": "You are capable, truly.",
      "serbian": "Ти си способан, заиста.",
      "transliteration": "Ti si sposoban, zaista.",
      "category": "Strength",
      "generated_at": "2026-06-21T18:14:52.603493"
    },
    {
      "english": "Resilience, is your gift.",
      "serbian": "Отпорност, је твој дар.",
      "transliteration": "Otpornost, je tvoj dar.",
      "category": "Strength",
      "generated_at": "2026-06-21T18:14:52.603494"
    },
    {
      "english": "Push forward, always forward.",
      "serbian": "Гури напред, увек напред.",
      "transliteration": "Guri napred, uvek napred.",
      "category": "Strength",
      "generated_at": "2026-06-21T18:14:52.603496"
    },
    {
      "english": "My heart, beats for you.",
      "serbian": "Moje srce, kuca za tebe.",
      "transliteration": "Mo-ye sr-tse, ku-cha za te-be.",
      "category": "Love",
      "generated_at": "2026-06-21T21:17:59.997100"
    },
    {
      "english": "You are, my everything.",
      "serbian": "Ti si, sve moje.",
      "transliteration": "Ti si, sve mo-ye.",
      "category": "Love",
      "generated_at": "2026-06-21T21:17:59.997110"
    },
    {
      "english": "I love you, more each day.",
      "serbian": "Volim te, sve više svaki dan.",
      "transliteration": "Vo-lim te, sve vi-she sva-ki dan.",
      "category": "Love",
      "generated_at": "2026-06-21T21:17:59.997112"
    },
    {
      "english": "Thinking of you, always.",
      "serbian": "Mislim na tebe, stalno.",
      "transliteration": "Mi-slim na te-be, stal-no.",
      "category": "Love",
      "generated_at": "2026-06-21T21:17:59.997113"
    },
    {
      "english": "You make me, so happy.",
      "serbian": "Činiš me, veoma srećnim/srećnom.",
      "transliteration": "Chi-nish me, ve-o-ma sre-chnim/sre-chnom.",
      "category": "Love",
      "generated_at": "2026-06-21T21:17:59.997115"
    },
    {
      "english": "You can do this, breathe deep.",
      "serbian": "Možeš ovo, duboko udahni.",
      "transliteration": "Mo-zhesh o-vo, du-bo-ko u-dah-ni.",
      "category": "Confidence",
      "generated_at": "2026-06-22T03:58:27.230139"
    },
    {
      "english": "One word at a time.",
      "serbian": "Jedna reč, po jedna.",
      "transliteration": "Yed-na rech, po yed-na.",
      "category": "Confidence",
      "generated_at": "2026-06-22T03:58:27.230146"
    },
    {
      "english": "Don't worry, just try.",
      "serbian": "Ne brini, samo pokušaj.",
      "transliteration": "Ne bri-ni, sa-mo po-ku-shaj.",
      "category": "Confidence",
      "generated_at": "2026-06-22T03:58:27.230148"
    },
    {
      "english": "Every mistake, is learning.",
      "serbian": "Svaka greška, je učenje.",
      "transliteration": "Sva-ka gresh-ka, ye oo-chen-ye.",
      "category": "Confidence",
      "generated_at": "2026-06-22T03:58:27.230150"
    },
    {
      "english": "Speak slowly, clearly.",
      "serbian": "Govori polako, jasno.",
      "transliteration": "Go-vo-ri po-la-ko, yas-no.",
      "category": "Confidence",
      "generated_at": "2026-06-22T03:58:27.230151"
    },
    {
      "english": "Grateful for everything, really.",
      "serbian": "Захвалан/захвална за све, стварно.",
      "transliteration": "Zahvalan/zahvalna za sve, stvarno.",
      "category": "Gratitude",
      "generated_at": "2026-06-22T16:54:07.833144"
    },
    {
      "english": "My thanks, go with you.",
      "serbian": "Моје хвале, иду с вама.",
      "transliteration": "Moje hvale, idu s vama.",
      "category": "Gratitude",
      "generated_at": "2026-06-22T16:54:07.833152"
    },
    {
      "english": "Thank you, from my heart.",
      "serbian": "Хвала, од срца.",
      "transliteration": "Hvala, od srca.",
      "category": "Gratitude",
      "generated_at": "2026-06-22T16:54:07.833154"
    },
    {
      "english": "Forever grateful, I am.",
      "serbian": "Вечно захвалан/захвална, сам.",
      "transliteration": "Večno zahvalan/zahvalna, sam.",
      "category": "Gratitude",
      "generated_at": "2026-06-22T16:54:07.833155"
    },
    {
      "english": "Much appreciated, thank you.",
      "serbian": "Много цењено, хвала.",
      "transliteration": "Mnogo cenjeno, hvala.",
      "category": "Gratitude",
      "generated_at": "2026-06-22T16:54:07.833156"
    },
    {
      "english": "Listen well, speak wisely.",
      "serbian": "Slušaj pažljivo, govori mudro.",
      "transliteration": "Slushay pazhljivo, govori mudro.",
      "category": "Wisdom",
      "generated_at": "2026-06-22T18:16:11.024148"
    },
    {
      "english": "Learn daily, grow always.",
      "serbian": "Uči svaki dan, rasti uvek.",
      "transliteration": "Uchi svaki dan, rasti uvek.",
      "category": "Wisdom",
      "generated_at": "2026-06-22T18:16:11.024155"
    },
    {
      "english": "Be patient, achieve much.",
      "serbian": "Budi strpljiv, postigni mnogo.",
      "transliteration": "Budi strpljiv, postigni mnogo.",
      "category": "Wisdom",
      "generated_at": "2026-06-22T18:16:11.024156"
    },
    {
      "english": "Small steps, big progress.",
      "serbian": "Mali koraci, veliki napredak.",
      "transliteration": "Mali koraci, veliki napredak.",
      "category": "Wisdom",
      "generated_at": "2026-06-22T18:16:11.024157"
    },
    {
      "english": "Seek truth, find clarity.",
      "serbian": "Traži istinu, nađi jasnoću.",
      "transliteration": "Trazi istinu, nadyi jasnochu.",
      "category": "Wisdom",
      "generated_at": "2026-06-22T18:16:11.024159"
    },
    {
      "english": "It's my pleasure.",
      "serbian": "Задовољство је моје.",
      "transliteration": "Zadovoljstvo je moje.",
      "category": "Common Expressions",
      "generated_at": "2026-06-22T20:00:14.678948"
    },
    {
      "english": "I understand, completely.",
      "serbian": "Разумем, потпуно.",
      "transliteration": "Razumem, potpuno.",
      "category": "Common Expressions",
      "generated_at": "2026-06-22T20:00:14.678957"
    },
    {
      "english": "Don't worry, about it.",
      "serbian": "Не брини, око тога.",
      "transliteration": "Ne brini, oko toga.",
      "category": "Common Expressions",
      "generated_at": "2026-06-22T20:00:14.678959"
    },
    {
      "english": "Welcome, everyone.",
      "serbian": "Добродошли, сви.",
      "transliteration": "Dobrodošli, svi.",
      "category": "Common Expressions",
      "generated_at": "2026-06-22T20:00:14.678960"
    },
    {
      "english": "That's great, really.",
      "serbian": "То је сјајно, заиста.",
      "transliteration": "To je sjajno, zaista.",
      "category": "Common Expressions",
      "generated_at": "2026-06-22T20:00:14.678961"
    },
    {
      "english": "Learn a little, every day.",
      "serbian": "Uči malo, svaki dan.",
      "transliteration": "Uchi malo, svaki dan.",
      "category": "Growth",
      "generated_at": "2026-06-22T22:06:18.345086"
    },
    {
      "english": "Mistakes are, learning moments.",
      "serbian": "Greške su, trenuci učenja.",
      "transliteration": "Greshke su, trenuci uchenja.",
      "category": "Growth",
      "generated_at": "2026-06-22T22:06:18.345095"
    },
    {
      "english": "Speak slowly, listen closely.",
      "serbian": "Govori polako, slušaj pažljivo.",
      "transliteration": "Govori polako, slushai pazhljivo.",
      "category": "Growth",
      "generated_at": "2026-06-22T22:06:18.345097"
    },
    {
      "english": "Practice makes, progress happen.",
      "serbian": "Vežba čini, napredak se dešava.",
      "transliteration": "Vezhba chini, napredak se deshavva.",
      "category": "Growth",
      "generated_at": "2026-06-22T22:06:18.345098"
    },
    {
      "english": "Be patient, with yourself.",
      "serbian": "Budi strpljiv, sa sobom.",
      "transliteration": "Budi strpljiv, sa sobom.",
      "category": "Growth",
      "generated_at": "2026-06-22T22:06:18.345099"
    },
    {
      "english": "Now, or never.",
      "serbian": "Сада, или никад.",
      "transliteration": "Sada, ili nikad.",
      "category": "Time",
      "generated_at": "2026-06-23T02:56:45.870988"
    },
    {
      "english": "Later, maybe. Soon, definitely.",
      "serbian": "Касније, можда. Ускоро, сигурно.",
      "transliteration": "Kasnije, možda. Uskoro, sigurno.",
      "category": "Time",
      "generated_at": "2026-06-23T02:56:45.870997"
    },
    {
      "english": "Every moment, counts.",
      "serbian": "Сваки тренутак, је важан.",
      "transliteration": "Svaki trenutak, je važan.",
      "category": "Time",
      "generated_at": "2026-06-23T02:56:45.870999"
    },
    {
      "english": "Time flies, when happy.",
      "serbian": "Време лети, кад је лепо.",
      "transliteration": "Vreme leti, kad je lepo.",
      "category": "Time",
      "generated_at": "2026-06-23T02:56:45.871000"
    },
    {
      "english": "Don't waste, precious time.",
      "serbian": "Не троши, драго време.",
      "transliteration": "Ne troši, drago vreme.",
      "category": "Time",
      "generated_at": "2026-06-23T02:56:45.871001"
    },
    {
      "english": "Breathe deep, find calm.",
      "serbian": "Диши дубоко, нађи мир.",
      "transliteration": "Diši duboko, nađi mir.",
      "category": "Inner Peace",
      "generated_at": "2026-06-23T16:31:03.246285"
    },
    {
      "english": "Quiet mind, gentle heart.",
      "serbian": "Миран ум, благ ум.",
      "transliteration": "Miran um, blag um.",
      "category": "Inner Peace",
      "generated_at": "2026-06-23T16:31:03.246295"
    },
    {
      "english": "Inner stillness, true strength.",
      "serbian": "Унутрашња тишина, права снага.",
      "transliteration": "Unutrašnja tišina, prava snaga.",
      "category": "Inner Peace",
      "generated_at": "2026-06-23T16:31:03.246297"
    },
    {
      "english": "Let go, feel free.",
      "serbian": "Пусти, осети слободу.",
      "transliteration": "Pusti, oseti slobodu.",
      "category": "Inner Peace",
      "generated_at": "2026-06-23T16:31:03.246298"
    },
    {
      "english": "Today is a gift.",
      "serbian": "Данас је дар.",
      "transliteration": "Danas je dar.",
      "category": "Inner Peace",
      "generated_at": "2026-06-23T16:31:03.246299"
    },
    {
      "english": "Believe in yourself, always.",
      "serbian": "Veruj u sebe, uvek.",
      "transliteration": "Veruy u sebe, uvek.",
      "category": "Hope",
      "generated_at": "2026-06-23T19:02:53.950827"
    },
    {
      "english": "Good things take time.",
      "serbian": "Dobre stvari, traju.",
      "transliteration": "Dobre stvari, traju.",
      "category": "Hope",
      "generated_at": "2026-06-23T19:02:53.950836"
    },
    {
      "english": "Never give up, try again.",
      "serbian": "Nikad ne odustaj, probaj.",
      "transliteration": "Nikad ne odustay, probay.",
      "category": "Hope",
      "generated_at": "2026-06-23T19:02:53.950838"
    },
    {
      "english": "Tomorrow is a new day.",
      "serbian": "Sutra je novi dan.",
      "transliteration": "Sutra ye novi dan.",
      "category": "Hope",
      "generated_at": "2026-06-23T19:02:53.950839"
    },
    {
      "english": "Keep moving forward, slowly.",
      "serbian": "Idi napred, polako.",
      "transliteration": "Idi napred, polako.",
      "category": "Hope",
      "generated_at": "2026-06-23T19:02:53.950840"
    },
    {
      "english": "Be patient, my friend.",
      "serbian": "Буди стрпљив, пријатељу.",
      "transliteration": "Budi strpljiv, prijatelju.",
      "category": "Patience",
      "generated_at": "2026-06-23T21:44:44.042211"
    },
    {
      "english": "Little by little, we grow.",
      "serbian": "Мало по мало, растемо.",
      "transliteration": "Malo po malo, rastemo.",
      "category": "Patience",
      "generated_at": "2026-06-23T21:44:44.042219"
    },
    {
      "english": "Wait and see, what happens.",
      "serbian": "Сачекај и види, шта ће бити.",
      "transliteration": "Sačekaj i vidi, šta će biti.",
      "category": "Patience",
      "generated_at": "2026-06-23T21:44:44.042221"
    },
    {
      "english": "The reward, is worth it.",
      "serbian": "Награда, вреди труда.",
      "transliteration": "Nagrada, vredi truda.",
      "category": "Patience",
      "generated_at": "2026-06-23T21:44:44.042223"
    },
    {
      "english": "Just breathe, and wait.",
      "serbian": "Само диши, и чекај.",
      "transliteration": "Samo diši, i čekaj.",
      "category": "Patience",
      "generated_at": "2026-06-23T21:44:44.042224"
    },
    {
      "english": "Be present, be happy.",
      "serbian": "Буди присутан, буди срећан.",
      "transliteration": "Budi prisutan, budi srećan.",
      "category": "Happiness",
      "generated_at": "2026-06-24T02:57:30.161492"
    },
    {
      "english": "Love what you do.",
      "serbian": "Воли то што радиш.",
      "transliteration": "Voli to što radiš.",
      "category": "Happiness",
      "generated_at": "2026-06-24T02:57:30.161501"
    },
    {
      "english": "Every moment counts.",
      "serbian": "Сваки тренутак се рачуна.",
      "transliteration": "Svaki trenutak se računa.",
      "category": "Happiness",
      "generated_at": "2026-06-24T02:57:30.161503"
    },
    {
      "english": "Gratitude brings happiness.",
      "serbian": "Захвалност доноси срећу.",
      "transliteration": "Zahvalnost donosi sreću.",
      "category": "Happiness",
      "generated_at": "2026-06-24T02:57:30.161504"
    },
    {
      "english": "Spread kindness, feel joy.",
      "serbian": "Шири доброту, осети радост.",
      "transliteration": "Širi dobrotu, oseti radost.",
      "category": "Happiness",
      "generated_at": "2026-06-24T02:57:30.161505"
    },
    {
      "english": "Where is the, fitting room?",
      "serbian": "Где је, свлачионица?",
      "transliteration": "Gde je, svlačionica?",
      "category": "Shopping",
      "generated_at": "2026-06-24T14:26:27.136681"
    },
    {
      "english": "I need, a bag, please.",
      "serbian": "Треба ми, торба, молим.",
      "transliteration": "Treba mi, torba, molim.",
      "category": "Shopping",
      "generated_at": "2026-06-24T14:26:27.136690"
    },
    {
      "english": "Do you accept, credit cards?",
      "serbian": "Примате ли, кредитне картице?",
      "transliteration": "Primate li, kreditne kartice?",
      "category": "Shopping",
      "generated_at": "2026-06-24T14:26:27.136691"
    },
    {
      "english": "I will take, this one.",
      "serbian": "Узећу, ово.",
      "transliteration": "Uzeću, ovo.",
      "category": "Shopping",
      "generated_at": "2026-06-24T14:26:27.136692"
    },
    {
      "english": "Thank you, for your help.",
      "serbian": "Хвала, на помоћи.",
      "transliteration": "Hvala, na pomoći.",
      "category": "Shopping",
      "generated_at": "2026-06-24T14:26:27.136694"
    },
    {
      "english": "Learn Serbian, for fun.",
      "serbian": "Uči srpski, radi zabave.",
      "transliteration": "Uchi srpski, radi zabave.",
      "category": "Purpose",
      "generated_at": "2026-06-24T16:28:04.303127"
    },
    {
      "english": "Speak Serbian, with confidence.",
      "serbian": "Govori srpski, sa samopouzdanjem.",
      "transliteration": "Govori srpski, sa samopouzdanjem.",
      "category": "Purpose",
      "generated_at": "2026-06-24T16:28:04.303136"
    },
    {
      "english": "Understand Serbian, quickly.",
      "serbian": "Razumi srpski, brzo.",
      "transliteration": "Razumi srpski, brzo.",
      "category": "Purpose",
      "generated_at": "2026-06-24T16:28:04.303138"
    },
    {
      "english": "Connect with Serbs, easily.",
      "serbian": "Poveži se sa Srbima, lako.",
      "transliteration": "Poveži se sa Srbima, lako.",
      "category": "Purpose",
      "generated_at": "2026-06-24T16:28:04.303140"
    },
    {
      "english": "Travel Serbia, like a local.",
      "serbian": "Putuj Srbijom, kao meštanin.",
      "transliteration": "Putuj Srbijom, kao meštanin.",
      "category": "Purpose",
      "generated_at": "2026-06-24T16:28:04.303141"
    },
    {
      "english": "We understand each other, well.",
      "serbian": "Razumemo se, dobro.",
      "transliteration": "Razumemo se, dobro.",
      "category": "Friendship",
      "generated_at": "2026-06-24T18:27:36.973309"
    },
    {
      "english": "Always there, for me.",
      "serbian": "Uvek tu, za mene.",
      "transliteration": "Uvek tu, za mene.",
      "category": "Friendship",
      "generated_at": "2026-06-24T18:27:36.973319"
    },
    {
      "english": "You make me laugh, a lot.",
      "serbian": "Nasmejavaš me, mnogo.",
      "transliteration": "Nasmejavaš me, mnogo.",
      "category": "Friendship",
      "generated_at": "2026-06-24T18:27:36.973321"
    },
    {
      "english": "Glad you're here, friend.",
      "serbian": "Drago mi je, što si tu, prijatelju.",
      "transliteration": "Drago mi je, što si tu, prijatelju.",
      "category": "Friendship",
      "generated_at": "2026-06-24T18:27:36.973322"
    },
    {
      "english": "Our friendship, is special.",
      "serbian": "Naše prijateljstvo, je posebno.",
      "transliteration": "Naše prijateljstvo, je posebno.",
      "category": "Friendship",
      "generated_at": "2026-06-24T18:27:36.973323"
    },
    {
      "english": "Make memories, that last.",
      "serbian": "Прави успомене, за памћење.",
      "transliteration": "Pravi uspomene, za pamćenje.",
      "category": "Positive Life",
      "generated_at": "2026-06-24T21:33:37.727992"
    },
    {
      "english": "Learn much, laugh often.",
      "serbian": "Учи много, смеј се често.",
      "transliteration": "Uči mnogo, smej se često.",
      "category": "Positive Life",
      "generated_at": "2026-06-24T21:33:37.728002"
    },
    {
      "english": "Believe in yourself, you can.",
      "serbian": "Веруј у себе, можеш.",
      "transliteration": "Veruj u sebe, možeš.",
      "category": "Positive Life",
      "generated_at": "2026-06-24T21:33:37.728004"
    },
    {
      "english": "Share your light, with world.",
      "serbian": "Дели своју светлост, са светом.",
      "transliteration": "Deli svoju svetlost, sa svetom.",
      "category": "Positive Life",
      "generated_at": "2026-06-24T21:33:37.728005"
    },
    {
      "english": "Embrace change, it's growth.",
      "serbian": "Прихвати промене, то је раст.",
      "transliteration": "Prihvati promene, to je rast.",
      "category": "Positive Life",
      "generated_at": "2026-06-24T21:33:37.728006"
    },
    {
      "english": "Explore, discover, build.",
      "serbian": "Истражуј, откривај, гради.",
      "transliteration": "Istražuj, otkrivaj, gradi.",
      "category": "Creativity",
      "generated_at": "2026-06-25T02:57:36.900825"
    },
    {
      "english": "Unleash your inner artist.",
      "serbian": "Ослободи свог уметника.",
      "transliteration": "Oslobodi svog umetnika.",
      "category": "Creativity",
      "generated_at": "2026-06-25T02:57:36.900834"
    },
    {
      "english": "Every detail matters.",
      "serbian": "Сваки детаљ је важан.",
      "transliteration": "Svaki detalj je važan.",
      "category": "Creativity",
      "generated_at": "2026-06-25T02:57:36.900836"
    },
    {
      "english": "Dream, then do.",
      "serbian": "Сањај, па уради.",
      "transliteration": "Sanjaj, pa uradi.",
      "category": "Creativity",
      "generated_at": "2026-06-25T02:57:36.900837"
    },
    {
      "english": "Create your own path.",
      "serbian": "Створи свој пут.",
      "transliteration": "Stvori svoj put.",
      "category": "Creativity",
      "generated_at": "2026-06-25T02:57:36.900838"
    },
    {
      "english": "Each lesson, a new door opens.",
      "serbian": "Svaka lekcija, otvara se nova vrata.",
      "transliteration": "Svaka lekcija, otvara se nova vrata.",
      "category": "Success",
      "generated_at": "2026-06-27T13:29:15.609427"
    },
    {
      "english": "Your voice, getting stronger each day.",
      "serbian": "Tvoj glas, jači svakim danom.",
      "transliteration": "Tvoj glas, jači svakim danom.",
      "category": "Success",
      "generated_at": "2026-06-27T13:29:15.609436"
    },
    {
      "english": "Embrace the challenge, find your rhythm.",
      "serbian": "Prihvati izazov, pronađi svoj ritam.",
      "transliteration": "Prihvati izazov, pronađi svoj ritam.",
      "category": "Success",
      "generated_at": "2026-06-27T13:29:15.609437"
    },
    {
      "english": "From single words, a story unfolds.",
      "serbian": "Od reči do reči, priča se razvija.",
      "transliteration": "Od reči do reči, priča se razvija.",
      "category": "Success",
      "generated_at": "2026-06-27T13:29:15.609438"
    },
    {
      "english": "This journey, incredibly rewarding.",
      "serbian": "Ovo putovanje, neverovatno nagrađuje.",
      "transliteration": "Ovo putovanje, neverovatno nagrađuje.",
      "category": "Success",
      "generated_at": "2026-06-27T13:29:15.609439"
    },
    {
      "english": "My heart aches, please let go.",
      "serbian": "Srce me boli, molim te, pusti.",
      "transliteration": "Srce me boli, molim te, pusti.",
      "category": "Forgiveness",
      "generated_at": "2026-06-27T15:21:28.555239"
    },
    {
      "english": "Let peace be our guide now.",
      "serbian": "Neka mir bude naš vodič sada.",
      "transliteration": "Neka mir bude naš vodič sada.",
      "category": "Forgiveness",
      "generated_at": "2026-06-27T15:21:28.555248"
    },
    {
      "english": "I regret deeply, truly.",
      "serbian": "Duboko žalim, iskreno.",
      "transliteration": "Duboko žalim, iskreno.",
      "category": "Forgiveness",
      "generated_at": "2026-06-27T15:21:28.555249"
    },
    {
      "english": "Can we heal this wound?",
      "serbian": "Možemo li izlečiti ovu ranu?",
      "transliteration": "Možemo li izlečiti ovu ranu?",
      "category": "Forgiveness",
      "generated_at": "2026-06-27T15:21:28.555251"
    },
    {
      "english": "I release the past, with you.",
      "serbian": "Oslobađam prošlost, sa tobom.",
      "transliteration": "Oslobađam prošlost, sa tobom.",
      "category": "Forgiveness",
      "generated_at": "2026-06-27T15:21:28.555252"
    },
    {
      "english": "Start your day, with coffee.",
      "serbian": "Počni dan, sa kafom.",
      "transliteration": "Poch-nee dahn, sah kah-fom.",
      "category": "Work",
      "generated_at": "2026-06-27T17:55:24.806720"
    },
    {
      "english": "Let's get to work, team.",
      "serbian": "Idemo na posao, tim.",
      "transliteration": "Ee-deh-moh nah poh-sah-loh, teem.",
      "category": "Work",
      "generated_at": "2026-06-27T17:55:24.806729"
    },
    {
      "english": "This task, needs attention.",
      "serbian": "Ovaj zadatak, traži pažnju.",
      "transliteration": "Oh-vai zah-dah-tahk, trah-zhee pahzh-nyoo.",
      "category": "Work",
      "generated_at": "2026-06-27T17:55:24.806731"
    },
    {
      "english": "Can you help me, please?",
      "serbian": "Možeš li mi pomoći, molim?",
      "transliteration": "Moh-zhesh lee mee poh-moh-chee, moh-leem?",
      "category": "Work",
      "generated_at": "2026-06-27T17:55:24.806732"
    },
    {
      "english": "I have a question, for you.",
      "serbian": "Imam pitanje, za tebe.",
      "transliteration": "Ee-mahm pee-tah-nyeh, zah teh-beh.",
      "category": "Work",
      "generated_at": "2026-06-27T17:55:24.806733"
    },
    {
      "english": "Step forward, boldly.",
      "serbian": "Крени напред, одлучно.",
      "transliteration": "Kreni napred, odlučno.",
      "category": "Courage",
      "generated_at": "2026-06-27T21:08:24.497632"
    },
    {
      "english": "Trust your gut, always.",
      "serbian": "Веруј инстинкту, увек.",
      "transliteration": "Veruj instinktu, uvek.",
      "category": "Courage",
      "generated_at": "2026-06-27T21:08:24.497642"
    },
    {
      "english": "Embrace the unknown, seeker.",
      "serbian": "Прихвати непознато, трагаоче.",
      "transliteration": "Prihvati nepoznato, tragaoche.",
      "category": "Courage",
      "generated_at": "2026-06-27T21:08:24.497644"
    },
    {
      "english": "Your spirit, shines bright.",
      "serbian": "Твој дух, сија јако.",
      "transliteration": "Tvoj duh, sija jako.",
      "category": "Courage",
      "generated_at": "2026-06-27T21:08:24.497645"
    },
    {
      "english": "Push past limits, now.",
      "serbian": "Пробиј границе, сада.",
      "transliteration": "Probij granice, sada.",
      "category": "Courage",
      "generated_at": "2026-06-27T21:08:24.497646"
    },
    {
      "english": "The sky, is clear today.",
      "serbian": "Nebo, je vedro danas.",
      "transliteration": "Nebo, ye vedro danas.",
      "category": "Weather",
      "generated_at": "2026-06-28T03:33:51.477458"
    },
    {
      "english": "It's raining, quite heavily.",
      "serbian": "Pada kiša, prilično jako.",
      "transliteration": "Pada kiša, prilično yako.",
      "category": "Weather",
      "generated_at": "2026-06-28T03:33:51.477466"
    },
    {
      "english": "A gentle breeze, is blowing.",
      "serbian": "Duva blagi povetarac.",
      "transliteration": "Duva blagi povetarac.",
      "category": "Weather",
      "generated_at": "2026-06-28T03:33:51.477468"
    },
    {
      "english": "The sun, is shining brightly.",
      "serbian": "Sunce, sija jako.",
      "transliteration": "Sunce, siya yako.",
      "category": "Weather",
      "generated_at": "2026-06-28T03:33:51.477469"
    },
    {
      "english": "There's fog, in the morning.",
      "serbian": "Jutros, je magla.",
      "transliteration": "Yutros, ye magla.",
      "category": "Weather",
      "generated_at": "2026-06-28T03:33:51.477470"
    },
    {
      "english": "Offer a helping hand, gently.",
      "serbian": "Pruži ruku pomoći, nežno.",
      "transliteration": "Pruzhi ruku pomoci, nezno.",
      "category": "Kindness",
      "generated_at": "2026-06-28T13:42:30.885483"
    },
    {
      "english": "A kind word, goes far.",
      "serbian": "Ljubazna reč, daleko stiže.",
      "transliteration": "Ljubazna rech, daleko stizhe.",
      "category": "Kindness",
      "generated_at": "2026-06-28T13:42:30.885491"
    },
    {
      "english": "See the good, in others.",
      "serbian": "Vidi dobro, u drugima.",
      "transliteration": "Vidi dobro, u drugima.",
      "category": "Kindness",
      "generated_at": "2026-06-28T13:42:30.885493"
    },
    {
      "english": "Spread some light, today.",
      "serbian": "Raširi malo svetla, danas.",
      "transliteration": "Rashiri malo svetla, danas.",
      "category": "Kindness",
      "generated_at": "2026-06-28T13:42:30.885495"
    },
    {
      "english": "Empathy, opens hearts.",
      "serbian": "Empatija, otvara srca.",
      "transliteration": "Empatija, otvara srca.",
      "category": "Kindness",
      "generated_at": "2026-06-28T13:42:30.885496"
    },
    {
      "english": "Save wisely, live fully.",
      "serbian": "Штеди паметно, живи пуно.",
      "transliteration": "Shtedi pametno, zhivi puno.",
      "category": "Finance",
      "generated_at": "2026-06-28T15:22:38.578133"
    },
    {
      "english": "Invest in dreams, not doubts.",
      "serbian": "Уложи у снове, не у сумње.",
      "transliteration": "Ulozhi u snove, ne u sumnje.",
      "category": "Finance",
      "generated_at": "2026-06-28T15:22:38.578142"
    },
    {
      "english": "Budget your goals, achieve them.",
      "serbian": "Буџетирај циљеве, постигни их.",
      "transliteration": "Budzhetiraj ciljeve, postigni ih.",
      "category": "Finance",
      "generated_at": "2026-06-28T15:22:38.578144"
    },
    {
      "english": "Plan your money, own your future.",
      "serbian": "Планирај новац, владај будућношћу.",
      "transliteration": "Planiraj novats, vladaj buduchnoshcu.",
      "category": "Finance",
      "generated_at": "2026-06-28T15:22:38.578145"
    },
    {
      "english": "Grow your wealth, slowly.",
      "serbian": "Расти богатство, полако.",
      "transliteration": "Rasti bogatstvo, polako.",
      "category": "Finance",
      "generated_at": "2026-06-28T15:22:38.578146"
    },
    {
      "english": "Sun shines, birds sing.",
      "serbian": "Sunce sija, ptice pevaju.",
      "transliteration": "Soontseh see-yah, pteet-seh peh-vah-yoo.",
      "category": "Nature",
      "generated_at": "2026-06-28T17:59:21.558314"
    },
    {
      "english": "Green forest, cool shade.",
      "serbian": "Zelena šuma, hladovina.",
      "transliteration": "Zeh-leh-nah shoo-mah, khlah-doh-vee-nah.",
      "category": "Nature",
      "generated_at": "2026-06-28T17:59:21.558323"
    },
    {
      "english": "River flows, water gleams.",
      "serbian": "Reka teče, voda blista.",
      "transliteration": "Reh-kah teh-cheh, voh-dah blees-tah.",
      "category": "Nature",
      "generated_at": "2026-06-28T17:59:21.558324"
    },
    {
      "english": "Mountain high, clouds drift.",
      "serbian": "Visoka planina, oblaci plove.",
      "transliteration": "Vee-soh-kah plah-nee-nah, oh-blah-tsee ploh-veh.",
      "category": "Nature",
      "generated_at": "2026-06-28T17:59:21.558325"
    },
    {
      "english": "Wind whispers, leaves dance.",
      "serbian": "Vetar šušti, lišće igra.",
      "transliteration": "Veh-tahr shoosh-tee, leesh-cheh ee-grah.",
      "category": "Nature",
      "generated_at": "2026-06-28T17:59:21.558327"
    },
    {
      "english": "Breathe in peace, breathe out worries.",
      "serbian": "Udahni mir, izdahni brige.",
      "transliteration": "Udahn mir, izdahni brige.",
      "category": "Mindfulness",
      "generated_at": "2026-06-28T21:05:34.989753"
    },
    {
      "english": "Feel the moment, let it flow.",
      "serbian": "Oseti trenutak, pusti da teče.",
      "transliteration": "Oseti trenutak, pusti da teče.",
      "category": "Mindfulness",
      "generated_at": "2026-06-28T21:05:34.989763"
    },
    {
      "english": "Stillness within, calm outside.",
      "serbian": "Tišina u tebi, mir spolja.",
      "transliteration": "Tišina u tebi, mir spolja.",
      "category": "Mindfulness",
      "generated_at": "2026-06-28T21:05:34.989765"
    },
    {
      "english": "Listen closely, to your heart.",
      "serbian": "Slušaj pažljivo, svoje srce.",
      "transliteration": "Slušaj pažljivo, svoje srce.",
      "category": "Mindfulness",
      "generated_at": "2026-06-28T21:05:34.989767"
    },
    {
      "english": "Ground yourself, with each step.",
      "serbian": "Uzemlji se, svakim korakom.",
      "transliteration": "Uzemlji se, svakim korakom.",
      "category": "Mindfulness",
      "generated_at": "2026-06-28T21:05:34.989768"
    },
    {
      "english": "This view, is breathtaking.",
      "serbian": "Ovaj pogled, oduzima dah.",
      "transliteration": "Ovaj pogled, oduzima dah.",
      "category": "Travel",
      "generated_at": "2026-06-29T03:38:21.992324"
    },
    {
      "english": "Could you recommend, a local dish?",
      "serbian": "Možete li preporučiti, lokalno jelo?",
      "transliteration": "Možete li preporučiti, lokalno jelo?",
      "category": "Travel",
      "generated_at": "2026-06-29T03:38:21.992333"
    },
    {
      "english": "Where can I find, good coffee?",
      "serbian": "Gde mogu naći, dobru kafu?",
      "transliteration": "Gde mogu naći, dobru kafu?",
      "category": "Travel",
      "generated_at": "2026-06-29T03:38:21.992335"
    },
    {
      "english": "This music, is wonderful.",
      "serbian": "Ova muzika, je divna.",
      "transliteration": "Ova muzika, je divna.",
      "category": "Travel",
      "generated_at": "2026-06-29T03:38:21.992336"
    },
    {
      "english": "I'm looking for, a quiet street.",
      "serbian": "Tražim, mirnu ulicu.",
      "transliteration": "Tražim, mirnu ulicu.",
      "category": "Travel",
      "generated_at": "2026-06-29T03:38:21.992337"
    },
    {
      "english": "Unlock the rhythm, of Serbian words.",
      "serbian": "Otključaj ritam, srpskih reči.",
      "transliteration": "Otkljuchay ritam, srpskih rechi.",
      "category": "Inspiration",
      "generated_at": "2026-06-29T15:43:09.289073"
    },
    {
      "english": "A new language, a new world awaits.",
      "serbian": "Novi jezik, novi svet čeka.",
      "transliteration": "Novi yezik, novi svet cheka.",
      "category": "Inspiration",
      "generated_at": "2026-06-29T15:43:09.289080"
    },
    {
      "english": "Listen closely, the sounds will guide you.",
      "serbian": "Slušaj pažljivo, zvukovi će te voditi.",
      "transliteration": "Slushay pazhljivo, zvukovi tchete voditi.",
      "category": "Inspiration",
      "generated_at": "2026-06-29T15:43:09.289082"
    },
    {
      "english": "Every conversation, a small victory.",
      "serbian": "Svaki razgovor, mala pobeda.",
      "transliteration": "Svaki razgovor, mala pobeda.",
      "category": "Inspiration",
      "generated_at": "2026-06-29T15:43:09.289083"
    },
    {
      "english": "Embrace the challenge, find your fluency.",
      "serbian": "Prihvati izazov, pronađi tečnost.",
      "transliteration": "Prihvati izazov, pronađi techost.",
      "category": "Inspiration",
      "generated_at": "2026-06-29T15:43:09.289084"
    },
    {
      "english": "Sing your heart out, loud and clear.",
      "serbian": "Pevaj iz srca, glasno i jasno.",
      "transliteration": "Pevay eez sertsah, glasno ee yasno.",
      "category": "Music",
      "generated_at": "2026-06-29T16:56:59.487486"
    },
    {
      "english": "Listen to the rhythm, feel the beat.",
      "serbian": "Slušaj ritam, oseti takt.",
      "transliteration": "Slooshay reetam, oseti takt.",
      "category": "Music",
      "generated_at": "2026-06-29T16:56:59.487495"
    },
    {
      "english": "Dance like nobody's watching, truly free.",
      "serbian": "Igraj kao niko ne gleda, potpuno slobodno.",
      "transliteration": "Eegra y kao neeko ne gledah, potpoono slobodyno.",
      "category": "Music",
      "generated_at": "2026-06-29T16:56:59.487496"
    },
    {
      "english": "Play that melody, a sweet refrain.",
      "serbian": "Odsviraj tu melodiju, sladak refren.",
      "transliteration": "Odsveervay too melodeeyoo, sladak refren.",
      "category": "Music",
      "generated_at": "2026-06-29T16:56:59.487498"
    },
    {
      "english": "Hum a happy tune, all day long.",
      "serbian": "Huči veselu melodiju, ceo dan.",
      "transliteration": "Hoo-chee veseloo melodeeyoo, tseh-oh dan.",
      "category": "Music",
      "generated_at": "2026-06-29T16:56:59.487499"
    },
    {
      "english": "The cat, sleeps on the mat.",
      "serbian": "Мачка, спава на простирци.",
      "transliteration": "Machka, spava na prostirci.",
      "category": "Animals",
      "generated_at": "2026-06-29T18:58:55.804438"
    },
    {
      "english": "A dog, barks at the door.",
      "serbian": "Пас, лаје на врата.",
      "transliteration": "Pas, laje na vrata.",
      "category": "Animals",
      "generated_at": "2026-06-29T18:58:55.804446"
    },
    {
      "english": "Birds, sing in the trees.",
      "serbian": "Птице, певају у дрвећу.",
      "transliteration": "Ptice, pevaju u drveću.",
      "category": "Animals",
      "generated_at": "2026-06-29T18:58:55.804447"
    },
    {
      "english": "Fish, swim in the river.",
      "serbian": "Рибе, пливају у реци.",
      "transliteration": "Ribe, plivaju u reci.",
      "category": "Animals",
      "generated_at": "2026-06-29T18:58:55.804449"
    },
    {
      "english": "The horse, runs through the field.",
      "serbian": "Коњ, трчи кроз поље.",
      "transliteration": "Konj, trchi kroz polje.",
      "category": "Animals",
      "generated_at": "2026-06-29T18:58:55.804450"
    },
    {
      "english": "Breathe deep, feel calm.",
      "serbian": "Дубоко диши, осети мир.",
      "transliteration": "Duboko diši, oseti mir.",
      "category": "Health",
      "generated_at": "2026-06-29T21:38:11.064785"
    },
    {
      "english": "Hydrate well, stay strong.",
      "serbian": "Пиј пуно воде, остани јак.",
      "transliteration": "Pij puno vode, ostani jak.",
      "category": "Health",
      "generated_at": "2026-06-29T21:38:11.064793"
    },
    {
      "english": "Eat smart, live long.",
      "serbian": "Једи паметно, живи дуго.",
      "transliteration": "Jedi pametno, živi dugo.",
      "category": "Health",
      "generated_at": "2026-06-29T21:38:11.064795"
    },
    {
      "english": "Move your body, feel good.",
      "serbian": "Помери тело, осети се добро.",
      "transliteration": "Pomeri telo, oseti se dobro.",
      "category": "Health",
      "generated_at": "2026-06-29T21:38:11.064796"
    },
    {
      "english": "Sleep soundly, wake refreshed.",
      "serbian": "Спавај мирно, буди се одморан.",
      "transliteration": "Spavaj mirno, budi se odmoran.",
      "category": "Health",
      "generated_at": "2026-06-29T21:38:11.064797"
    },
    {
      "english": "Sunrise paints the sky, a new day begins.",
      "serbian": "Sunce boji nebo, nov dan počinje.",
      "transliteration": "Sun-tse bo-yi ne-bo, nov dan po-chi-nye.",
      "category": "Daily Routine",
      "generated_at": "2026-06-30T03:25:33.939255"
    },
    {
      "english": "Stretch, yawn, and greet the morning.",
      "serbian": "Protegni se, zevaj, i pozdravi jutro.",
      "transliteration": "Pro-teg-ni se, ze-vay, i poz-dra-vi yu-tro.",
      "category": "Daily Routine",
      "generated_at": "2026-06-30T03:25:33.939265"
    },
    {
      "english": "First coffee, then conquer the world.",
      "serbian": "Prva kafa, pa osvoji svet.",
      "transliteration": "Pr-va ka-fa, pa os-vo-yi svet.",
      "category": "Daily Routine",
      "generated_at": "2026-06-30T03:25:33.939266"
    },
    {
      "english": "Shower away, sleepiness is gone.",
      "serbian": "Istuširaj se, pospanost je nestala.",
      "transliteration": "Is-tu-shi-ray se, pos-pa-nost ye nes-ta-la.",
      "category": "Daily Routine",
      "generated_at": "2026-06-30T03:25:33.939268"
    },
    {
      "english": "Brush teeth, smile bright.",
      "serbian": "Operi zube, osmeh blista.",
      "transliteration": "O-pe-ri zu-be, os-meh blis-ta.",
      "category": "Daily Routine",
      "generated_at": "2026-06-30T03:25:33.939269"
    },
    {
      "english": "Just one moment, please.",
      "serbian": "Samo trenutak, molim.",
      "transliteration": "Samo trenutak, molim.",
      "category": "Numbers",
      "generated_at": "2026-06-30T14:15:28.191232"
    },
    {
      "english": "Two friends, met today.",
      "serbian": "Dvoje drugara, srelo se danas.",
      "transliteration": "Dvoje drugara, srelo se danas.",
      "category": "Numbers",
      "generated_at": "2026-06-30T14:15:28.191242"
    },
    {
      "english": "Three coins, in the fountain.",
      "serbian": "Tri novčića, u fontani.",
      "transliteration": "Tri novčića, u fontani.",
      "category": "Numbers",
      "generated_at": "2026-06-30T14:15:28.191243"
    },
    {
      "english": "Four seasons, pass quickly.",
      "serbian": "Četiri godišnja doba, prolaze brzo.",
      "transliteration": "Četiri godišnja doba, prolaze brzo.",
      "category": "Numbers",
      "generated_at": "2026-06-30T14:15:28.191244"
    },
    {
      "english": "Six more, to go.",
      "serbian": "Još šest, do cilja.",
      "transliteration": "Još šest, do cilja.",
      "category": "Numbers",
      "generated_at": "2026-06-30T14:15:28.191246"
    },
    {
      "english": "A little bit, later.",
      "serbian": "Malo, kasnije.",
      "transliteration": "Malo, kasnije.",
      "category": "Common Expressions",
      "generated_at": "2026-06-30T16:26:31.209243"
    },
    {
      "english": "Here you go, then.",
      "serbian": "Evo ti, onda.",
      "transliteration": "Evo ti, onda.",
      "category": "Common Expressions",
      "generated_at": "2026-06-30T16:26:31.209252"
    },
    {
      "english": "Just like that, yes.",
      "serbian": "Tako, da.",
      "transliteration": "Tako, da.",
      "category": "Common Expressions",
      "generated_at": "2026-06-30T16:26:31.209254"
    },
    {
      "english": "Maybe, sometime soon.",
      "serbian": "Možda, uskoro.",
      "transliteration": "Možda, uskoro.",
      "category": "Common Expressions",
      "generated_at": "2026-06-30T16:26:31.209255"
    },
    {
      "english": "Right this way, please.",
      "serbian": "Ovuda, molim.",
      "transliteration": "Ovuda, molim.",
      "category": "Common Expressions",
      "generated_at": "2026-06-30T16:26:31.209256"
    },
    {
      "english": "Find your calm, then move.",
      "serbian": "Nađi svoj mir, onda kreni.",
      "transliteration": "Nadi svoj mir, onda kreni.",
      "category": "Balance",
      "generated_at": "2026-06-30T18:28:47.294718"
    },
    {
      "english": "Steady hand, clear mind.",
      "serbian": "Mirna ruka, bistar um.",
      "transliteration": "Mirna ruka, bistar um.",
      "category": "Balance",
      "generated_at": "2026-06-30T18:28:47.294728"
    },
    {
      "english": "Breathe deep, step light.",
      "serbian": "Diši duboko, koračaj lako.",
      "transliteration": "Disi duboko, koracaj lako.",
      "category": "Balance",
      "generated_at": "2026-06-30T18:28:47.294730"
    },
    {
      "english": "Center yourself, then soar.",
      "serbian": "Usredsredi se, pa poleti.",
      "transliteration": "Usredsredi se, pa poleti.",
      "category": "Balance",
      "generated_at": "2026-06-30T18:28:47.294732"
    },
    {
      "english": "Grounded feet, reaching sky.",
      "serbian": "Uzemljene noge, dosežeš nebo.",
      "transliteration": "Uzemljene noge, dosezes nebo.",
      "category": "Balance",
      "generated_at": "2026-06-30T18:28:47.294733"
    },
    {
      "english": "Open mind, open heart, open world.",
      "serbian": "Otvoren um, otvoreno srce, otvoren svet.",
      "transliteration": "Otvoren um, otvoreno srce, otvoren svet.",
      "category": "Wisdom",
      "generated_at": "2026-06-30T21:41:30.177671"
    },
    {
      "english": "Listen to silence, learn its lessons.",
      "serbian": "Slušaj tišinu, nauči njene lekcije.",
      "transliteration": "Slušaj tišinu, nauči njene lekcije.",
      "category": "Wisdom",
      "generated_at": "2026-06-30T21:41:30.177681"
    },
    {
      "english": "Every day, a new beginning.",
      "serbian": "Svaki dan, novi početak.",
      "transliteration": "Svaki dan, novi početak.",
      "category": "Wisdom",
      "generated_at": "2026-06-30T21:41:30.177682"
    },
    {
      "english": "Embrace change, find your strength.",
      "serbian": "Prihvati promene, pronađi svoju snagu.",
      "transliteration": "Prihvati promene, pronađi svoju snagu.",
      "category": "Wisdom",
      "generated_at": "2026-06-30T21:41:30.177683"
    },
    {
      "english": "Curiosity lights the path ahead.",
      "serbian": "Znatiželja osvetljava put napred.",
      "transliteration": "Znatiželja osvetljava put napred.",
      "category": "Wisdom",
      "generated_at": "2026-06-30T21:41:30.177684"
    },
    {
      "english": "This, is, beautiful.",
      "serbian": "Ovo, je, prelepo.",
      "transliteration": "Ovo, ye, prelepo.",
      "category": "Basic Phrases",
      "generated_at": "2026-07-01T03:35:05.571873"
    },
    {
      "english": "Can, I, help, you?",
      "serbian": "Mogu, li, da, pomognem?",
      "transliteration": "Mogu, li, da, pomognem?",
      "category": "Basic Phrases",
      "generated_at": "2026-07-01T03:35:05.571883"
    },
    {
      "english": "Where, is, the, station?",
      "serbian": "Gde, je, stanica?",
      "transliteration": "Gde, ye, stanitsa?",
      "category": "Basic Phrases",
      "generated_at": "2026-07-01T03:35:05.571885"
    },
    {
      "english": "I, like, this, food.",
      "serbian": "Volim, ovu, hranu.",
      "transliteration": "Volim, ovu, hranu.",
      "category": "Basic Phrases",
      "generated_at": "2026-07-01T03:35:05.571886"
    },
    {
      "english": "It, is, very, good.",
      "serbian": "Veoma, je, dobro.",
      "transliteration": "Veoma, ye, dobro.",
      "category": "Basic Phrases",
      "generated_at": "2026-07-01T03:35:05.571887"
    },
    {
      "english": "My hand, it reaches.",
      "serbian": "Moja ruka, ona pruža.",
      "transliteration": "Moy-ah roo-kah, oh-nah proo-zhah.",
      "category": "Body Parts",
      "generated_at": "2026-07-01T14:31:33.933273"
    },
    {
      "english": "Your eyes, they see.",
      "serbian": "Tvoje oči, one vide.",
      "transliteration": "Tvoy-eh oh-chee, oh-neh vee-deh.",
      "category": "Body Parts",
      "generated_at": "2026-07-01T14:31:33.933282"
    },
    {
      "english": "His foot, it walks.",
      "serbian": "Njegova noga, ona hoda.",
      "transliteration": "Nye-go-vah no-gah, oh-nah ho-dah.",
      "category": "Body Parts",
      "generated_at": "2026-07-01T14:31:33.933284"
    },
    {
      "english": "Her mouth, it speaks.",
      "serbian": "Njena usta, ona govore.",
      "transliteration": "Nye-nah oo-stah, oh-nah go-vo-reh.",
      "category": "Body Parts",
      "generated_at": "2026-07-01T14:31:33.933285"
    },
    {
      "english": "Our head, it thinks.",
      "serbian": "Naša glava, ona misli.",
      "transliteration": "Nah-shah glah-vah, oh-nah mees-lee.",
      "category": "Body Parts",
      "generated_at": "2026-07-01T14:31:33.933286"
    },
    {
      "english": "The sky, a vibrant blue.",
      "serbian": "Nebo, žarko plavo.",
      "transliteration": "Nebo, zharko plavo.",
      "category": "Colors",
      "generated_at": "2026-07-01T16:32:19.448708"
    },
    {
      "english": "Grass green, life grows.",
      "serbian": "Trava zelena, život raste.",
      "transliteration": "Trava zelena, zhivot raste.",
      "category": "Colors",
      "generated_at": "2026-07-01T16:32:19.448717"
    },
    {
      "english": "Sun yellow, warm light.",
      "serbian": "Sunce žuto, topla svetlost.",
      "transliteration": "Sunce zhuto, topla svetlost.",
      "category": "Colors",
      "generated_at": "2026-07-01T16:32:19.448719"
    },
    {
      "english": "Rose red, a soft bloom.",
      "serbian": "Ruža crvena, nežan cvet.",
      "transliteration": "Ruzha crvena, nezhan cvet.",
      "category": "Colors",
      "generated_at": "2026-07-01T16:32:19.448720"
    },
    {
      "english": "Ocean deep, navy shades.",
      "serbian": "Okean dubok, mornarske nijanse.",
      "transliteration": "Okean dubok, mornarske nijanse.",
      "category": "Colors",
      "generated_at": "2026-07-01T16:32:19.448721"
    },
    {
      "english": "Taste the rakija, feel the warmth.",
      "serbian": "Okusi rakiju, oseti toplinu.",
      "transliteration": "Okusi rakiju, oseti toplinu.",
      "category": "Culture",
      "generated_at": "2026-07-01T18:55:20.463039"
    },
    {
      "english": "The music plays, the kolo spins.",
      "serbian": "Sviraju note, kolo se vrti.",
      "transliteration": "Sviraju note, kolo se vrti.",
      "category": "Culture",
      "generated_at": "2026-07-01T18:55:20.463050"
    },
    {
      "english": "Burek for breakfast, a daily joy.",
      "serbian": "Burek za doručak, dnevna radost.",
      "transliteration": "Burek za doručak, dnevna radost.",
      "category": "Culture",
      "generated_at": "2026-07-01T18:55:20.463052"
    },
    {
      "english": "A smile, a greeting, hospitality's start.",
      "serbian": "Osmeh, pozdrav, početak gostoprimstva.",
      "transliteration": "Osmeh, pozdrav, početak gostoprimstva.",
      "category": "Culture",
      "generated_at": "2026-07-01T18:55:20.463053"
    },
    {
      "english": "History whispers, in ancient stones.",
      "serbian": "Istorija šapuće, u starom kamenju.",
      "transliteration": "Istorija šapuće, u starom kamenju.",
      "category": "Culture",
      "generated_at": "2026-07-01T18:55:20.463054"
    },
    {
      "english": "Listen to the silence, within you.",
      "serbian": "Slušaj tišinu, u sebi.",
      "transliteration": "Slush-ah tee-shee-noo, oo seh-bee.",
      "category": "Inner Peace",
      "generated_at": "2026-07-01T21:40:32.222044"
    },
    {
      "english": "The present moment, is all there is.",
      "serbian": "Sadašnji trenutak, je sve što postoji.",
      "transliteration": "Sah-dahsh-nee tren-oo-tak, yeh sveh sh'toh poh-stoy-ee.",
      "category": "Inner Peace",
      "generated_at": "2026-07-01T21:40:32.222054"
    },
    {
      "english": "Flow like water, find your way.",
      "serbian": "Teci kao voda, nađi svoj put.",
      "transliteration": "Teh-tsee kah-oh voh-dah, nah-dzee svoy poot.",
      "category": "Inner Peace",
      "generated_at": "2026-07-01T21:40:32.222056"
    },
    {
      "english": "Peace blooms, from acceptance.",
      "serbian": "Mir cveta, iz prihvatanja.",
      "transliteration": "Meer tsvay-tah, eez pree-khvah-tah-nyah.",
      "category": "Inner Peace",
      "generated_at": "2026-07-01T21:40:32.222057"
    },
    {
      "english": "Your true north, guides you home.",
      "serbian": "Tvoj pravi sever, vodi te kući.",
      "transliteration": "Tvoy prah-vee seh-ver, voh-dee teh koo-chee.",
      "category": "Inner Peace",
      "generated_at": "2026-07-01T21:40:32.222059"
    },
    {
      "english": "Sunshine, warm breeze, happy sigh.",
      "serbian": "Sunce, topli povetarac, srećan uzdah.",
      "transliteration": "Sunce, topli povetarac, srećan uzdah.",
      "category": "Happiness",
      "generated_at": "2026-07-02T02:58:33.251847"
    },
    {
      "english": "Little wins, big smiles.",
      "serbian": "Male pobede, veliki osmesi.",
      "transliteration": "Male pobede, veliki osmesi.",
      "category": "Happiness",
      "generated_at": "2026-07-02T02:58:33.251856"
    },
    {
      "english": "Comforting tea, quiet evening, inner calm.",
      "serbian": "Utešan čaj, mirno veče, unutrašnji mir.",
      "transliteration": "Utešan čaj, mirno veče, unutrašnji mir.",
      "category": "Happiness",
      "generated_at": "2026-07-02T02:58:33.251858"
    },
    {
      "english": "Dancing freely, singing loudly, feeling alive.",
      "serbian": "Plešem slobodno, pevam glasno, osećam se živim.",
      "transliteration": "Plesem slobodno, pevam glasno, osećam se živim.",
      "category": "Happiness",
      "generated_at": "2026-07-02T02:58:33.251859"
    },
    {
      "english": "A good book, a cozy corner, pure contentment.",
      "serbian": "Dobra knjiga, udoban kutak, čisto zadovoljstvo.",
      "transliteration": "Dobra knjiga, udoban kutak, čisto zadovoljstvo.",
      "category": "Happiness",
      "generated_at": "2026-07-02T02:58:33.251860"
    },
    {
      "english": "Discover Serbian soul, one word at a time.",
      "serbian": "Otkrijte srpsku dušu, reč po reč.",
      "transliteration": "Otkrijte srpsku dušu, reč po reč.",
      "category": "Purpose",
      "generated_at": "2026-07-02T13:55:13.041775"
    },
    {
      "english": "Unlock vibrant culture, through language.",
      "serbian": "Otključajte živopisnu kulturu, jezikom.",
      "transliteration": "Otključajte živopisnu kulturu, jezikom.",
      "category": "Purpose",
      "generated_at": "2026-07-02T13:55:13.041784"
    },
    {
      "english": "Build bridges, with Serbian fluency.",
      "serbian": "Gradite mostove, tečno govoreći srpski.",
      "transliteration": "Gradite mostove, tečno govoreći srpski.",
      "category": "Purpose",
      "generated_at": "2026-07-02T13:55:13.041785"
    },
    {
      "english": "Explore rich history, with new words.",
      "serbian": "Istražite bogatu istoriju, novim rečima.",
      "transliteration": "Istražite bogatu istoriju, novim rečima.",
      "category": "Purpose",
      "generated_at": "2026-07-02T13:55:13.041787"
    },
    {
      "english": "Taste Serbian life, one phrase daily.",
      "serbian": "Ukusite srpski život, frazu dnevno.",
      "transliteration": "Ukusite srpski život, frazu dnevno.",
      "category": "Purpose",
      "generated_at": "2026-07-02T13:55:13.041788"
    },
    {
      "english": "I'm feeling very unwell, suddenly.",
      "serbian": "Odjednom mi je jako loše.",
      "transliteration": "Od-yed-nom mee yeh ya-ko lo-sheh.",
      "category": "Emergency",
      "generated_at": "2026-07-02T18:22:55.786260"
    },
    {
      "english": "Can you direct me, to safety?",
      "serbian": "Možete li me uputiti, na sigurno?",
      "transliteration": "Mo-zheh-teh lee meh oo-poo-tee-tee, nah see-goor-no?",
      "category": "Emergency",
      "generated_at": "2026-07-02T18:22:55.786279"
    },
    {
      "english": "My breathing, is very difficult.",
      "serbian": "Veoma mi je teško, da dišem.",
      "transliteration": "Veh-o-ma mee yeh tehsh-ko, da dee-shem.",
      "category": "Emergency",
      "generated_at": "2026-07-02T18:22:55.786281"
    },
    {
      "english": "Is there anyone, who speaks English?",
      "serbian": "Ima li iko, ko govori engleski?",
      "transliteration": "Ee-ma lee ee-ko, ko go-vo-ree eng-les-kee?",
      "category": "Emergency",
      "generated_at": "2026-07-02T18:22:55.786282"
    },
    {
      "english": "I've had an accident, unfortunately.",
      "serbian": "Doživeo/Doživela sam nesreću, nažalost.",
      "transliteration": "Do-zhee-veh-o/Do-zhee-veh-la sahm neh-sre-choo, nah-zha-lost.",
      "category": "Emergency",
      "generated_at": "2026-07-02T18:22:55.786283"
    },
    {
      "english": "Focus now, on this goal.",
      "serbian": "Fokusirajte se sada, na ovaj cilj.",
      "transliteration": "Fokusirajte se sada, na ovaj cilj.",
      "category": "Work",
      "generated_at": "2026-07-02T21:11:23.670192"
    },
    {
      "english": "Let's finish this, quickly.",
      "serbian": "Završimo ovo, brzo.",
      "transliteration": "Završimo ovo, brzo.",
      "category": "Work",
      "generated_at": "2026-07-02T21:11:23.670201"
    },
    {
      "english": "New idea, for the project.",
      "serbian": "Nova ideja, za projekat.",
      "transliteration": "Nova ideja, za projekat.",
      "category": "Work",
      "generated_at": "2026-07-02T21:11:23.670203"
    },
    {
      "english": "This deadline, is approaching.",
      "serbian": "Ovaj rok, se približava.",
      "transliteration": "Ovaj rok, se približava.",
      "category": "Work",
      "generated_at": "2026-07-02T21:11:23.670204"
    },
    {
      "english": "We need to brainstorm, today.",
      "serbian": "Moramo da razmišljamo, danas.",
      "transliteration": "Moramo da razmišljamo, danas.",
      "category": "Work",
      "generated_at": "2026-07-02T21:11:23.670206"
    },
    {
      "english": "Your voice, matters here.",
      "serbian": "Твој глас, овде је важан.",
      "transliteration": "Tvoj glas, ovde je važan.",
      "category": "Confidence",
      "generated_at": "2026-07-03T02:42:31.830081"
    },
    {
      "english": "Let your words, bloom.",
      "serbian": "Нека твоје речи, цветају.",
      "transliteration": "Neka tvoje reči, cvetaju.",
      "category": "Confidence",
      "generated_at": "2026-07-03T02:42:31.830091"
    },
    {
      "english": "Embrace the journey, with joy.",
      "serbian": "Прихвати пут, са радошћу.",
      "transliteration": "Prihvati put, sa radošću.",
      "category": "Confidence",
      "generated_at": "2026-07-03T02:42:31.830093"
    },
    {
      "english": "Each sentence, a step forward.",
      "serbian": "Свака реченица, корак напред.",
      "transliteration": "Svaka rečenica, korak napred.",
      "category": "Confidence",
      "generated_at": "2026-07-03T02:42:31.830094"
    },
    {
      "english": "Find your rhythm, in Serbian.",
      "serbian": "Нађи свој ритам, на српском.",
      "transliteration": "Nađi svoj ritam, na srpskom.",
      "category": "Confidence",
      "generated_at": "2026-07-03T02:42:31.830096"
    },
    {
      "english": "Joyful day, to you.",
      "serbian": "Радостан дан, вама.",
      "transliteration": "Radostan dan, vama.",
      "category": "Greetings",
      "generated_at": "2026-07-03T15:56:23.334790"
    },
    {
      "english": "Greetings, traveler.",
      "serbian": "Поздрав, путником.",
      "transliteration": "Pozdrav, putnikom.",
      "category": "Greetings",
      "generated_at": "2026-07-03T15:56:23.334802"
    },
    {
      "english": "Bright morning, my dear.",
      "serbian": "Светло јутро, драги мој.",
      "transliteration": "Svetlo jutro, dragi moj.",
      "category": "Greetings",
      "generated_at": "2026-07-03T15:56:23.334804"
    },
    {
      "english": "A pleasant hello, from me.",
      "serbian": "Пријатан поздрав, од мене.",
      "transliteration": "Prijatan pozdrav, od mene.",
      "category": "Greetings",
      "generated_at": "2026-07-03T15:56:23.334806"
    },
    {
      "english": "Warm welcome, friend.",
      "serbian": "Топли добродошлицу, пријатељу.",
      "transliteration": "Topli dobrodošlicu, prijatelju.",
      "category": "Greetings",
      "generated_at": "2026-07-03T15:56:23.334807"
    },
    {
      "english": "Learn Serbian, unlock new worlds.",
      "serbian": "Uči srpski, otvori nove svetove.",
      "transliteration": "Uchi srpski, otvori nove svetove.",
      "category": "Education",
      "generated_at": "2026-07-03T18:08:02.865746"
    },
    {
      "english": "Speak with confidence, my friend.",
      "serbian": "Pričaj sa poverenjem, moj prijatelju.",
      "transliteration": "Pritchaj sa poverenjem, moj prijatelju.",
      "category": "Education",
      "generated_at": "2026-07-03T18:08:02.865757"
    },
    {
      "english": "Every word, a step forward.",
      "serbian": "Svaka reč, korak napred.",
      "transliteration": "Svaka rech, korak napred.",
      "category": "Education",
      "generated_at": "2026-07-03T18:08:02.865759"
    },
    {
      "english": "Listen closely, understand deeply.",
      "serbian": "Slušaj pažljivo, razumi duboko.",
      "transliteration": "Slushaj pazhljivo, razumi duboko.",
      "category": "Education",
      "generated_at": "2026-07-03T18:08:02.865760"
    },
    {
      "english": "Practice makes perfect, you know.",
      "serbian": "Vežba čini majstora, znaš.",
      "transliteration": "Vezhba chini majstora, znash.",
      "category": "Education",
      "generated_at": "2026-07-03T18:08:02.865762"
    },
    {
      "english": "My best friend, since forever.",
      "serbian": "Moj najbolji prijatelj, od uvek.",
      "transliteration": "Moj najbolji prijatelj, od uvek.",
      "category": "Relationships",
      "generated_at": "2026-07-03T21:11:05.336302"
    },
    {
      "english": "We just clicked, you know?",
      "serbian": "Mi smo se razumeli, znaš?",
      "transliteration": "Mi smo se razumeli, znaš?",
      "category": "Relationships",
      "generated_at": "2026-07-03T21:11:05.336311"
    },
    {
      "english": "Family first, always.",
      "serbian": "Porodica na prvom mestu, uvek.",
      "transliteration": "Porodica na prvom mestu, uvek.",
      "category": "Relationships",
      "generated_at": "2026-07-03T21:11:05.336312"
    },
    {
      "english": "She's like a sister to me.",
      "serbian": "Ona mi je kao sestra.",
      "transliteration": "Ona mi je kao sestra.",
      "category": "Relationships",
      "generated_at": "2026-07-03T21:11:05.336314"
    },
    {
      "english": "He's my rock, really.",
      "serbian": "On je moja stena, stvarno.",
      "transliteration": "On je moja stena, stvarno.",
      "category": "Relationships",
      "generated_at": "2026-07-03T21:11:05.336315"
    },
    {
      "english": "Unlock new worlds, learn Serbian.",
      "serbian": "Otključajte nove svetove, naučite srpski.",
      "transliteration": "Otklyuchayte nove svetove, nauchite srpski.",
      "category": "Motivation",
      "generated_at": "2026-07-04T02:38:30.985979"
    },
    {
      "english": "Speak from the heart, speak Serbian.",
      "serbian": "Govorite iz srca, govorite srpski.",
      "transliteration": "Govorite iz srca, govorite srpski.",
      "category": "Motivation",
      "generated_at": "2026-07-04T02:38:30.985989"
    },
    {
      "english": "Every word, a new adventure.",
      "serbian": "Svaka reč, nova avantura.",
      "transliteration": "Svaka rech, nova avantura.",
      "category": "Motivation",
      "generated_at": "2026-07-04T02:38:30.985991"
    },
    {
      "english": "Connect deeper, learn Serbian.",
      "serbian": "Povežite se dublje, naučite srpski.",
      "transliteration": "Povezhit'e se dublye, nauchite srpski.",
      "category": "Motivation",
      "generated_at": "2026-07-04T02:38:30.985992"
    },
    {
      "english": "Your voice matters, in Serbian.",
      "serbian": "Vaš glas je bitan, na srpskom.",
      "transliteration": "Vash glas je bitan, na srpskom.",
      "category": "Motivation",
      "generated_at": "2026-07-04T02:38:30.985993"
    }
  ],
  "last_updated": "2026-07-04T02:38:30.985995"
}